drf_authenticator/__init__.py
drf_authenticator/authentication.py
drf_authenticator/exceptions.py
drf_authenticator/token.py
drf_authenticator-0.1.3.dist-info/METADATA
drf_authenticator-0.1.3.dist-info/WHEEL
drf_authenticator-0.1.3.dist-info/top_level.txt
drf_authenticator-0.1.3.dist-info/RECORD
